arctern_server/__init__.py
arctern_server/arctern-server
arctern_server/config.ini
arctern_server/manage.py
arctern_server/app/__init__.py
arctern_server/app/account.py
arctern_server/app/codegen.py
arctern_server/app/scope.py
arctern_server/app/service.py
arctern_server/app/common/__init__.py
arctern_server/app/common/config.py
arctern_server/app/common/db.py
arctern_server/app/common/log.py
arctern_server/app/common/spark.py
arctern_server/app/common/token.py
arctern_server/app/common/utils.py
arctern_server/data/0_5M_nyc_taxi_and_building.csv
arctern_server/data/account.db
arctern_server-0.0.4.data/scripts/arctern-server
arctern_server-0.0.4.dist-info/METADATA
arctern_server-0.0.4.dist-info/WHEEL
arctern_server-0.0.4.dist-info/top_level.txt
arctern_server-0.0.4.dist-info/RECORD
